{
  "resource": "/hello",
  "path": "/hello/",
  "httpMethod": "GET",
  "headers": {
    "Accept": "text/html,application/xhtml xml,application/xml;q=0.9,image/webp;q=0.8",
    "Accept-Encoding": "gzip, deflate, br",
    "Accept-Language": "en-US,en;q=0.5",
    "cache-control": "no-cache",
    "CloudFront-Forwarded-Proto": "https",
    "CloudFront-Is-Desktop-Viewer": "true",
    "CloudFront-Is-Mobile-Viewer": "false",
    "CloudFront-Is-SmartTV-Viewer": "false",
    "CloudFront-Is-Tablet-Viewer": "false",
    "CloudFront-Viewer-Country": "US",
    "dnt": "1",
    "Host": "gbx0plot4g.execute-api.us-east-1.amazonaws.com",
    "pragma": "no-cache",
    "upgrade-insecure-requests": "1",
    "User-Agent": "Mozilla/5.0 (Macintosh; Intel Mac OS X 10.15; rv:77.0) Gecko/20100101 Firefox/77.0",
    "Via": "2.0 a7ed0e2562a9e213a639323d1327bbbc.cloudfront.net (CloudFront)",
    "X-Amz-Cf-Id": "cvcTkyuwAKmHfi1fQoBQg0nygIYSG58vanIxKojixiYxQW_rLUGr3Q==",
    "X-Amzn-Trace-Id": "Root=1-5f00b1bd-6143aa8010fa8ec02626ab90",
    "X-Forwarded-For": "67.86.154.94, 130.176.33.95",
    "X-Forwarded-Port": "443",
    "X-Forwarded-Proto": "https"
  },
  "multiValueHeaders": {
    "Accept": [
      "text/html,application/xhtml xml,application/xml;q=0.9,image/webp,*/*;q=0.8"
    ],
    "Accept-Encoding": [
      "gzip, deflate, br"
    ],
    "Accept-Language": [
      "en-US,en;q=0.5"
    ],
    "cache-control": [
      "no-cache"
    ],
    "CloudFront-Forwarded-Proto": [
      "https"
    ],
    "CloudFront-Is-Desktop-Viewer": [
      "true"
    ],
    "CloudFront-Is-Mobile-Viewer": [
      "false"
    ],
    "CloudFront-Is-SmartTV-Viewer": [
      "false"
    ],
    "CloudFront-Is-Tablet-Viewer": [
      "false"
    ],
    "CloudFront-Viewer-Country": [
      "US"
    ],
    "dnt": [
      "1"
    ],
    "Host": [
      "gbx0plot4g.execute-api.us-east-1.amazonaws.com"
    ],
    "pragma": [
      "no-cache"
    ],
    "upgrade-insecure-requests": [
      "1"
    ],
    "User-Agent": [
      "Mozilla/5.0 (Macintosh; Intel Mac OS X 10.15; rv:77.0) Gecko/20100101 Firefox/77.0"
    ],
    "Via": [
      "2.0 a7ed0e2562a9e213a639323d1327bbbc.cloudfront.net (CloudFront)"
    ],
    "X-Amz-Cf-Id": [
      "cvcTkyuwAKmHfi1fQoBQg0nygIYSG58vanIxKojixiYxQW_rLUGr3Q=="
    ],
    "X-Amzn-Trace-Id": [
      "Root=1-5f00b1bd-6143aa8010fa8ec02626ab90"
    ],
    "X-Forwarded-For": [
      "67.86.154.94, 130.176.33.95"
    ],
    "X-Forwarded-Port": [
      "443"
    ],
    "X-Forwarded-Proto": [
      "https"
    ]
  },
  "queryStringParameters": null,
  "multiValueQueryStringParameters": null,
  "pathParameters": null,
  "stageVariables": null,
  "requestContext": {
    "resourceId": "1kpxsi",
    "resourcePath": "/hello",
    "httpMethod": "GET",
    "extendedRequestId": "PKC1pEaGIAMFycg=",
    "requestTime": "04/Jul/2020:16:43:41  0000",
    "path": "/Prod/hello/",
    "accountId": "443491358801",
    "protocol": "HTTP/1.1",
    "stage": "Prod",
    "domainPrefix": "gbx0plot4g",
    "requestTimeEpoch": 1593881021666,
    "requestId": "d93d8439-3e3a-43f4-aa8b-c974658e5dec",
    "identity": {
      "cognitoIdentityPoolId": null,
      "accountId": null,
      "cognitoIdentityId": null,
      "caller": null,
      "sourceIp": "67.86.154.94",
      "principalOrgId": null,
      "accessKey": null,
      "cognitoAuthenticationType": null,
      "cognitoAuthenticationProvider": null,
      "userArn": null,
      "userAgent": "Mozilla/5.0 (Macintosh; Intel Mac OS X 10.15; rv:77.0) Gecko/20100101 Firefox/77.0",
      "user": null
    },
    "domainName": "gbx0plot4g.execute-api.us-east-1.amazonaws.com",
    "apiId": "gbx0plot4g"
  },
  "body": null,
  "isBase64Encoded": false
}